colt5_attention/__init__.py
colt5_attention/attend.py
colt5_attention/coor_descent.py
colt5_attention/topk.py
colt5_attention/transformer_block.py
colt5_attention/triton_coor_descent.py
colt5_attention/vit.py
CoLT5_attention-0.11.1.dist-info/LICENSE
CoLT5_attention-0.11.1.dist-info/METADATA
CoLT5_attention-0.11.1.dist-info/WHEEL
CoLT5_attention-0.11.1.dist-info/top_level.txt
CoLT5_attention-0.11.1.dist-info/RECORD
